onnx_plaidml/__init__.py
onnx_plaidml/backend.py
onnx_plaidml/conversion.py
onnx_plaidml/opset_onnx.py
onnx_plaidml/opset_util.py
onnx_plaidml-0.6.3.dist-info/METADATA
onnx_plaidml-0.6.3.dist-info/WHEEL
onnx_plaidml-0.6.3.dist-info/entry_points.txt
onnx_plaidml-0.6.3.dist-info/top_level.txt
onnx_plaidml-0.6.3.dist-info/RECORD
