Metadata-Version: 2.1
Name: onnx-plaidml
Version: 0.6.3
Summary: PlaidML ONNX backend implementation.
Home-page: http://vertex.ai
Author: Intel Corporation
Author-email: eng@vertex.ai
License: https://www.gnu.org/licenses/agpl-3.0.en.html
Keywords: development ml onnx
Platform: UNKNOWN
Classifier: Development Status :: 3 - Alpha
Classifier: Intended Audience :: Developers
Classifier: Topic :: Scientific/Engineering :: Artificial Intelligence
Classifier: Topic :: Software Development
Classifier: License :: OSI Approved :: GNU Affero General Public License v3 or later (AGPLv3+)
Classifier: Operating System :: MacOS :: MacOS X
Classifier: Operating System :: Microsoft :: Windows :: Windows 10
Classifier: Operating System :: POSIX :: Linux
Classifier: Programming Language :: C++
Classifier: Programming Language :: Python :: 2.7
Classifier: Programming Language :: Python :: 3.5
Requires-Dist: click
Requires-Dist: numpy
Requires-Dist: onnx (==1.2.1)
Requires-Dist: plaidml (>=0.3.3)
Requires-Dist: six
